{"daily_2021-01.md":"56c2e10a","daily_2021-02.md":"c78a2cb8","daily_2021-03.md":"b0157bb1","daily_2021-04.md":"c9909098","daily_2021-05.md":"aed99cf5","daily_2021-06.md":"80b45936","daily_2021-07.md":"7a72c367","daily_2021-08.md":"87ac7aa4","daily_2021-09.md":"311594b7","daily_2021-10.md":"3016ec68","daily_2021-11.md":"59230f18","daily_2021-12.md":"f13b6399","daily_2022-01.md":"cbe88117","daily_2022-02.md":"0af20db9","daily_2022-03.md":"663d64b0","daily_2022-04.md":"9c71d6f2","daily_2022-05.md":"b7586aed","daily_2022-06.md":"a51a9817","daily_2022-07.md":"2cf59152","daily_2022-08.md":"74e8a137","daily_2022-09.md":"be2910e4","daily_2022-10.md":"6777e505","daily_2022-11.md":"664f1dd8","daily_2022-12.md":"000e539d","daily_2023-01.md":"cf281c0c","daily_index.md":"ae1f2a6c","index.md":"d88a0b2f","javascript_2021-12-31-md-icon.md":"0e4b2183","javascript_2022-05-07-git.md":"d18ed236","javascript_2022-05-10-vscode.md":"e3ad4d0d","javascript_2022-05-11-linux.md":"bd89aea9","javascript_2022-05-12-vue3.md":"de7b71f1","javascript_2022-05-15-guifan.md":"e1709577","javascript_2022-05-20-typescript.md":"f5055c55","javascript_2022-05-21-npm.md":"8e3c1ae6","javascript_2022-05-23-taro.md":"0ea5376d","javascript_2022-05-24-react.md":"20f09b31","javascript_2022-05-25-build-optimize.md":"fe3e2a57","javascript_2022-05-26-nodejs.md":"cddfca1f","javascript_2022-05-27-tauri.md":"00fef9c2","javascript_2022-05-28-mysql.md":"d16eadd9","javascript_2022-05-29-leaflet.md":"a04a063b","javascript_2022-05-30-javascript.md":"c6782ecc","javascript_2022-06-01-go.md":"84e97d12","javascript_2022-06-02-echarts.md":"8bc4df17","javascript_2022-06-03-ast.md":"660fc84c","javascript_2022-06-04-pnpm.md":"e9ee8a65","javascript_2022-06-05-router.md":"236763f8","javascript_2022-06-06-code.md":"7b1ba91c","javascript_2022-08-11-pnpm.md":"2ca8b550","javascript_2022-08-16-commitizen.md":"0287c472","javascript_2022-08-17-docker.md":"84a089af","javascript_2022-08-17-nginx.md":"80569ff3","javascript_2022-08-18-commit.md":"2eea1579","javascript_2022-08-18-taro.md":"392f0f59","javascript_2022-08-20-apifox.md":"2726d474","javascript_2022-08-22-nginx 负载均衡.md":"d5859618","javascript_2022-08-24-vim.md":"193e93a5","javascript_2022-08-25-hub docker.md":"31d6194f","javascript_2022-08-25-wujie.md":"1a8b2e67","javascript_2022-08-26-vue3原理.md":"e363c729","javascript_2022-08-31-.net core.md":"9eda25ea","javascript_2022-09-01-axios工具.md":"734cde32","javascript_2022-09-01-axios工具函数判断纯对象.md":"07020e13","javascript_2022-09-01-axios正则.md":"a53630c7","javascript_2022-09-01-javascript-ioc.md":"c37b344d","javascript_2022-09-21-history.md":"f0111ac7","javascript_2022-09-26-axios-utils.md":"e7ce4fe4","javascript_2022-10-09-http缓存.md":"16e563f9","javascript_2022-10-11-.net6.0.md":"b9c021ff","javascript_2022-10-15-后端.md":"fffb3401","javascript_2022-10-16-mysql.md":"b9bbdd2a","javascript_2022-10-26-redis.md":"d4e4c35f","javascript_2022-10-28-elasticsearch.md":"275e81a2","javascript_2022-11-06-docker.md":"d160c4a0","javascript_2022-11-08-字典.md":"5c41c512","javascript_2022-11-09-marridb.md":"db2bd3fa","javascript_2022-11-14-docker-mysql.md":"79ac1e76","javascript_2022-11-14-mysql-isnull-isnotnull.md":"0aabd0c7","javascript_2022-11-15-linux.md":"ceb6b1e7","javascript_2022-11-16-token.md":"c303ba33","javascript_2022-11-18-linux 监控指引.md":"4549ede2","javascript_2022-11-21-nginx.md":"9a328ef1","javascript_2022-11-23-aop.md":"7c212942","javascript_2022-11-23-mysql主从.md":"56b87cce","javascript_2022-11-23-环境配置.md":"857e3baf","javascript_2022-11-24-项目上线.md":"87049d83","javascript_2022-11-25-mysql删除重复数据.md":"af6bff9a","javascript_2022-11-26-linux mysql 慢查询.md":"e84489d2","javascript_2022-11-28-正则.md":"25eb066c","javascript_2022-11-30-.net-core异步.md":"cde01d9e","javascript_2022-12-01-docker-compose.md":"62c5b46a","javascript_2022-12-03-mysql学习了解总结.md":"b9e7e66a","javascript_2022-12-09-zx.md":"e0bcfa8e","javascript_2022-12-12-goploy.md":"449af126","javascript_2022-12-12-rabbitmq.md":"6ef26dfa","javascript_2022-12-14-linux.md":"ec668d18","javascript_2022-12-20-mysql.md":"683fa2fd","javascript_2022-12-20-ubuntu.md":"05ea4e8d","javascript_2022-12-20-zabbix.md":"527625c6","javascript_2022-12-21-总结.md":"aebb48cb","javascript_2022-12-28-linux.md":"ce6cd8bb","life_2021-12.md":"bd731141","life_2022-06.md":"35ce2590","life_2022-07.md":"1e8765b3","life_2022-0701.md":"2aa43bf1","life_index.md":"272be18a","me_about.md":"34e8ca27","me_index.md":"c6584e84"}
