{
  "hash": "90e1d216",
  "browserHash": "9117bbda",
  "optimized": {
    "vue": {
      "src": "../../../../node_modules/.pnpm/vue@3.4.5/node_modules/vue/dist/vue.runtime.esm-bundler.js",
      "file": "vue.js",
      "fileHash": "b8e690ee",
      "needsInterop": false
    },
    "axios": {
      "src": "../../../../node_modules/.pnpm/axios@0.27.2/node_modules/axios/index.js",
      "file": "axios.js",
      "fileHash": "860567cb",
      "needsInterop": true
    }
  },
  "chunks": {
    "chunk-76J2PTFD": {
      "file": "chunk-76J2PTFD.js"
    }
  }
}