[
  {
    "group": "crypto",
    "list": 
    [
      {
        "key":"futures-contract",
        "value": "2025-08-24-期货期权和永续合约非永续合约.html"
      },
      {
        "key":"futures-history",
        "value": "2025-08-23-期货的历史和发展.html"
      },
      {
        "key":"stablecoin-history",
        "value": "2025-08-19稳定币的历史.html"
      },
      {
        "key":"eth-history",
        "value": "2025-08-18-eth的历史.html"
      },
      {
        "key":"btc-history",
        "value": "2025-08-18-btc的历史.html"
      },
      {
        "key":"stablecoin",
        "value": "2025-07-13稳定币.html"
      },
      {
        "key": "blockchain",
        "value":"2025-07-15区块链技术全面指南.html"
      }
    ]
  },
  {
    "group": "policy",
    "list": 
    [
      {
         "key": "stock-flow",
         "value": "2025-08-23-存量和产量SF比值解析.html"
      },
      {
        "key": "hkd-exchange-rate",
        "value": "2025-07-18港币汇率.html"
      },
      {
        "key":"reverse-repo",
        "value": "2025-07-14央行买断式逆回购.html"
      }
    ]
  },
  {
    "group": "home",
    "list": 
    [
      {
        "key":"unit-basics",
        "value": "2025-07-17-生活中的单位换算详解.html"
      },
      {
        "key":"yadea-smart",
        "value": "2025-08-22-雅迪远程开关锁.html"
      },
      {
        "key":"ev-car",
        "value": "2025-08-22-电车远程操作.html"
      }
    ]
  }
]